catchment_data_api/__init__.py
catchment_data_api/catchment_data_api.py
catchment_data_api/cohorts.py
catchment_data_api/config_data/__init__.py
catchment_data_api/config_data/config.yaml
catchment_data_api/crops.py
catchment_data_api/database/__init__.py
catchment_data_api/database/livestock_land_cover_database
catchment_data_api/database_manager.py
catchment_data_api/static_data.py
catchment_data_api-0.1.3.dist-info/LICENSE
catchment_data_api-0.1.3.dist-info/METADATA
catchment_data_api-0.1.3.dist-info/WHEEL
catchment_data_api-0.1.3.dist-info/RECORD
